CHANGES.txt
LICENSE.txt
MANIFEST.in
README.rst
requirements.txt
setup.py
docs/index.rst
docs/operation.rst
docs/quickstart.rst
docs/_build/html/_sources/index.txt
docs/_build/html/_sources/operation.txt
docs/_build/html/_sources/quickstart.txt
statirator/__init__.py
statirator/main.py
statirator/test_settings.py
statirator.egg-info/PKG-INFO
statirator.egg-info/SOURCES.txt
statirator.egg-info/dependency_links.txt
statirator.egg-info/entry_points.txt
statirator.egg-info/not-zip-safe
statirator.egg-info/requires.txt
statirator.egg-info/top_level.txt
statirator/blog/locale/he/LC_MESSAGES/django.mo
statirator/blog/locale/he/LC_MESSAGES/django.po
statirator/blog/templates/blog/new_post_content.txt
statirator/blog/templates/blog/new_post_metadata.txt
statirator/blog/templates/blog/post_detail.html
statirator/blog/templates/blog/post_excerpt.html
statirator/blog/templates/blog/post_list.html
statirator/blog/templates/blog/tag_detail.html
statirator/blog/templates/blog/tag_list.html
statirator/core/templates/404.html
statirator/core/templates/base.html
statirator/core/templates/index.html
statirator/core/templates/sitemap.xml
statirator/project_template/manage.py
statirator/project_template/blog/README
statirator/project_template/locale/README
statirator/project_template/pages/.gitignore
statirator/project_template/pages/index.html
statirator/project_template/project_name/__init__.py
statirator/project_template/project_name/settings.py
statirator/project_template/project_name/urls.py
statirator/project_template/static/.htaccess
statirator/project_template/static/crossdomain.xml
statirator/project_template/static/favicon.ico
statirator/project_template/static/humans.txt
statirator/project_template/static/robots.txt
statirator/project_template/static/css/main.css
statirator/project_template/static/css/normalize.css
statirator/project_template/static/css/normalize_rtl.css
statirator/project_template/static/img/apple-touch-icon-114x114-precomposed.png
statirator/project_template/static/img/apple-touch-icon-144x144-precomposed.png
statirator/project_template/static/img/apple-touch-icon-57x57-precomposed.png
statirator/project_template/static/img/apple-touch-icon-72x72-precomposed.png
