Metadata-Version: 1.1
Name: statirator
Version: 0.2.0
Summary: Multilingual static site and blog generator
Home-page: http://pypi.python.org/pypi/statirator/
Author: Meir Kriheli
Author-email: mkriheli@gmail.com
License: LICENSE.txt
Platform: UNKNOWN
Classifier: Environment :: Web Environment
Classifier: Framework :: Django
Classifier: Intended Audience :: Developers
Classifier: License :: OSI Approved :: MIT License
Classifier: Programming Language :: Python
Classifier: Operating System :: OS Independent
Classifier: Topic :: Internet :: WWW/HTTP
